skill_recipes/LICENSE.md
skill_recipes/README.md
skill_recipes/__init__.py
skill_recipes/recipe_utils.py
skill_recipes/skill.json
skill_recipes/version.py
skill_recipes/dialog/en-us/CurrentRecipe.dialog
skill_recipes/dialog/en-us/CurrentStep.dialog
skill_recipes/dialog/en-us/IngredientQuantity.dialog
skill_recipes/dialog/en-us/NextStep.dialog
skill_recipes/dialog/en-us/NoIngredients.dialog
skill_recipes/dialog/en-us/NoInstructions.dialog
skill_recipes/dialog/en-us/NoNextSteps.dialog
skill_recipes/dialog/en-us/NoPreviousStep.dialog
skill_recipes/dialog/en-us/NoRecipe.dialog
skill_recipes/dialog/en-us/PreviousStep.dialog
skill_recipes/dialog/en-us/ReciteStep.dialog
skill_recipes/dialog/en-us/SearchFailed.dialog
skill_recipes/dialog/en-us/YouWillNeed.dialog
skill_recipes/neon_skill_recipes.egg-info/PKG-INFO
skill_recipes/neon_skill_recipes.egg-info/SOURCES.txt
skill_recipes/neon_skill_recipes.egg-info/dependency_links.txt
skill_recipes/neon_skill_recipes.egg-info/entry_points.txt
skill_recipes/neon_skill_recipes.egg-info/requires.txt
skill_recipes/neon_skill_recipes.egg-info/top_level.txt
skill_recipes/vocab/en-us/get.random.recipe.intent
skill_recipes/vocab/en-us/get.recipe.by.ingredient.intent
skill_recipes/vocab/en-us/get.recipe.by.name.intent
skill_recipes/vocab/en-us/get.the.current.step.intent
skill_recipes/vocab/en-us/get.the.ingredients.intent
skill_recipes/vocab/en-us/get.the.next.step.intent
skill_recipes/vocab/en-us/get.the.previous.step.intent
skill_recipes/vocab/en-us/get.the.recipe.name.intent
skill_recipes/vocab/en-us/recite.the.instructions.intent
neon_skill_recipes-0.0.1a10.dist-info/LICENSE.md
neon_skill_recipes-0.0.1a10.dist-info/METADATA
neon_skill_recipes-0.0.1a10.dist-info/WHEEL
neon_skill_recipes-0.0.1a10.dist-info/entry_points.txt
neon_skill_recipes-0.0.1a10.dist-info/top_level.txt
neon_skill_recipes-0.0.1a10.dist-info/RECORD
