Metadata-Version: 2.1
Name: neon-skill-recipes
Version: 0.0.1a10
Home-page: https://github.com/NeonGeckoCom/skill-recipes
Author: Neongecko
Author-email: developers@neon.ai
License: BSD-3-Clause
License-File: LICENSE.md
Requires-Dist: neon-utils~=1.12
Requires-Dist: ovos-utils>=0.0.28,~=0.0
Requires-Dist: ovos-workshop>=0.0.15,~=0.0
